commitbro/__init__.py
commitbro/cli.py
commitbro/core.py
commitbro/setup_config.py
commitbro/train.py
commitbro-0.1.0.dist-info/METADATA
commitbro-0.1.0.dist-info/WHEEL
commitbro-0.1.0.dist-info/entry_points.txt
commitbro-0.1.0.dist-info/RECORD
