Metadata-Version: 2.4
Name: commitbro
Version: 0.1.0
Summary: Generate Git commit messages using local or remote AI models.
Author-email: Himanshu Patel <dev@commitbro.privexamail.com>
Requires-Python: >=3.11
Requires-Dist: fastapi>=0.110
Requires-Dist: requests>=2.31
Requires-Dist: uvicorn[standard]>=0.29
